django_cms_superset_plugin/__init__.py
django_cms_superset_plugin/admin.py
django_cms_superset_plugin/apps.py
django_cms_superset_plugin/cms_plugins.py
django_cms_superset_plugin/forms.py
django_cms_superset_plugin/models.py
django_cms_superset_plugin/tests.py
django_cms_superset_plugin/views.py
django_cms_superset_plugin/templates/django_cms_superset_plugin/superset_plugin.html
django_cms_superset_plugin-1.0.0.dist-info/LICENSE
django_cms_superset_plugin-1.0.0.dist-info/METADATA
django_cms_superset_plugin-1.0.0.dist-info/WHEEL
django_cms_superset_plugin-1.0.0.dist-info/top_level.txt
django_cms_superset_plugin-1.0.0.dist-info/RECORD
