Metadata-Version: 2.1
Name: django-cms-superset-plugin
Version: 1.0.0
Summary: Django CMS plugin for embedding Superset dashboards.
Home-page: https://github.com/gabrielheck/django-cms-superset-plugin
Author: Gabriel Heck
Author-email: 
License: GNU GENERAL PUBLIC LICENSE 3.0
Classifier: Environment :: Web Environment
Classifier: Framework :: Django
Classifier: Intended Audience :: Developers
Classifier: Operating System :: OS Independent
Classifier: Programming Language :: Python
Classifier: Topic :: Internet :: WWW/HTTP
Classifier: Topic :: Internet :: WWW/HTTP :: Dynamic Content
Requires-Python: >=3.8
License-File: LICENSE
Requires-Dist: Django >=3.0
